VirtualEnvironment-0.1.2.data/data/src/VirtEnv/VirtEnv.py
VirtualEnvironment-0.1.2.data/data/src/VirtualEnvWriter.py/VirtualEnvWriter.py
VirtualEnvironment-0.1.2.data/scripts/run.sh
src/VirtEnv.py
src/VirtualEnvWriter.py
src/__init__.py
VirtualEnvironment-0.1.2.dist-info/LICENCE
VirtualEnvironment-0.1.2.dist-info/METADATA
VirtualEnvironment-0.1.2.dist-info/WHEEL
VirtualEnvironment-0.1.2.dist-info/top_level.txt
VirtualEnvironment-0.1.2.dist-info/RECORD
